fastapi_tools/cache/__init__.py
fastapi_tools/cache/cache.py
fastapi_tools/cache/config.py
fastapi_tools/cache/decorators.py
fastapi_tools/cache/protocol.py
fastapi_tools/cache/py.typed
fastapi_tools/cache/redis.py
fastapi_tools/cache/task.py
fastapi_tools_cache-0.1.10.dist-info/METADATA
fastapi_tools_cache-0.1.10.dist-info/WHEEL
fastapi_tools_cache-0.1.10.dist-info/RECORD
